Cybernator_disnake/Paginator.py
Cybernator_disnake/Rolegator.py
Cybernator_disnake/__init__.py
Cyberdisnake-1.0.0.dist-info/METADATA
Cyberdisnake-1.0.0.dist-info/WHEEL
Cyberdisnake-1.0.0.dist-info/top_level.txt
Cyberdisnake-1.0.0.dist-info/RECORD
