Metadata-Version: 2.1
Name: Cyberdisnake
Version: 1.0.0
Summary: Страницы по рекции disnake
Home-page: UNKNOWN
Author: NikaDevil
Author-email: ply123123q@gmail.com
License: UNKNOWN
Platform: UNKNOWN
Classifier: Programming Language :: Python :: 3
Classifier: License :: OSI Approved :: MIT License
Classifier: Operating System :: OS Independent
Requires-Python: >=3.6
